GHEpy/__init__.py
GHEpy/model/__init__.py
ghepy-0.1.0.dist-info/METADATA
ghepy-0.1.0.dist-info/WHEEL
ghepy-0.1.0.dist-info/RECORD
