Metadata-Version: 2.1
Name: ghepy
Version: 0.1.0
Summary: (Greenhouse energy-python) is a python tool for evaluation of heating demand in greenhouses when data are not provided elsewhere.
Author: Mehran Ahmadpour
Author-email: mehran.hmdpr@gmail.com
Requires-Python: >=3.8,<4.0
Classifier: Programming Language :: Python :: 3
Classifier: Programming Language :: Python :: 3.8
Classifier: Programming Language :: Python :: 3.9
Classifier: Programming Language :: Python :: 3.10
Classifier: Programming Language :: Python :: 3.11
Requires-Dist: coolprop (>=6.4.3.post1,<7.0.0)
Requires-Dist: folium (>=0.14.0,<0.15.0)
Requires-Dist: numpy (>=1.24.2,<2.0.0)
Requires-Dist: plotly (>=5.13.0,<6.0.0)
Requires-Dist: requests (>=2.28.2,<3.0.0)
Requires-Dist: vincent (>=0.4.4,<0.5.0)
